winterrb/classifications.py
winterrb/dataset.py
winterrb/model.py
winterrb/paths.py
winterrb/pick_alerts.py
winterrb/tree.py
winterrb/utils.py
winterrb-2.0.1.dist-info/licenses/LICENSE
winterrb-2.0.1.dist-info/METADATA
winterrb-2.0.1.dist-info/WHEEL
winterrb-2.0.1.dist-info/top_level.txt
winterrb-2.0.1.dist-info/RECORD
